{
  "generated_at": "2026-04-21T02:08:17.322Z",
  "filters_applied": {},
  "total_signals": 2,
  "total_available_signals": 2,
  "linked_signals": 2,
  "signals": [
    {
      "title": "Perfil publico principal",
      "description": "Camada publica principal para apresentacao e contexto profissional.",
      "href": "https://www.linkedin.com/in/danielle-amorim-31766435/",
      "value": "LinkedIn"
    },
    {
      "title": "Repositorio publico do perfil",
      "description": "Base publica para manutencao, versionamento e auditoria editorial.",
      "href": "https://github.com/mozgbrasil/node-vitepress-danielle",
      "value": "GitHub"
    }
  ]
}
